mpmcn.py
salome/bin/salome/test/CTestTestfile.cmake
salome/bin/salome/test/cpp/StudyGeneralTest
salome/bin/salome/test/cpp/SampleTest
salome/bin/salome/test/cpp/CTestTestfile.cmake
salome/bin/salome/test/cpp/StudyRestartTest
salome/bin/salome/test/pyexample/test_ydefx_base.py
salome/bin/salome/test/pyexample/test_default.py
salome/bin/salome/test/pyexample/CTestTestfile.cmake
salome/bin/salome/test/pyexample/runUnitTest.sh
salome/bin/salome/test/pyexample/test_prescript.py
salome/bin/salome/test/pyexample/test_mpmcn.py
salome/bin/salome/test/pyexample/test_insitu.py
salome/bin/salome/test/pyexample/insitu/insituiterator.py
salome/bin/salome/test/pyexample/insitu/insitumanager.py
pydefx/studyexception.py
pydefx/pyscript.py
pydefx/localbuilder.py
pydefx/multijobbuilder.py
pydefx/sample.py
pydefx/samplecsviterator.py
pydefx/defaultschemabuilder.py
pydefx/multijobstudy.py
pydefx/allpurposebuilder.py
pydefx/slurmstudy.py
pydefx/salome_proxy.py
pydefx/parameters.py
pydefx/slurmbuilder.py
pydefx/configuration.py
pydefx/localstudy.py
pydefx/pystudy.py
pydefx/studyresult.py
pydefx/samplecsvmanager.py
pydefx/__init__.py
pydefx/plugins/mainjob.py
pydefx/plugins/pointeval.py
pydefx/plugins/localexecutor.py
pydefx/plugins/lightexecutor.py
pydefx/plugins/jobexecutor.py
pydefx/plugins/srunexecutor.py
pydefx/schemas/plugin.py
pydefx/schemas/idefix_pyschema.xml
pydefx-9.14.0.post7.dist-info/METADATA
pydefx-9.14.0.post7.dist-info/WHEEL
pydefx-9.14.0.post7.dist-info/RECORD
